texterize/__init__.py
texterize/helpers/__init__.py
texterize/helpers/build_block.py
texterize/helpers/build_chroma.py
texterize/helpers/filter_text.py
texterize/helpers/write_file.py
texterize-1.0.12.dist-info/LICENSE
texterize-1.0.12.dist-info/METADATA
texterize-1.0.12.dist-info/WHEEL
texterize-1.0.12.dist-info/top_level.txt
texterize-1.0.12.dist-info/RECORD
