Metadata-Version: 2.1
Name: texterize
Version: 1.0.12
Summary: Making pictures worth a thousand words.
Home-page: https://github.com/cooperbarth/texterize
Author: Cooper Barth
Author-email: cooperfbarth@gmail.com
License: UNKNOWN
Platform: UNKNOWN
Classifier: Programming Language :: Python :: 3
Classifier: License :: OSI Approved :: MIT License
Classifier: Operating System :: OS Independent
Requires-Dist: numpy
Requires-Dist: python-docx
Requires-Dist: pillow
